fakeredis/__init__.py
fakeredis/_basefakesocket.py
fakeredis/_command_args_parsing.py
fakeredis/_commands.py
fakeredis/_connection.py
fakeredis/_fakesocket.py
fakeredis/_helpers.py
fakeredis/_msgs.py
fakeredis/_server.py
fakeredis/_tcp_server.py
fakeredis/_valkey.py
fakeredis/aioredis.py
fakeredis/commands.json
fakeredis/py.typed
fakeredis/typing.py
fakeredis/commands_mixins/__init__.py
fakeredis/commands_mixins/acl_mixin.py
fakeredis/commands_mixins/bitmap_mixin.py
fakeredis/commands_mixins/connection_mixin.py
fakeredis/commands_mixins/generic_mixin.py
fakeredis/commands_mixins/geo_mixin.py
fakeredis/commands_mixins/hash_mixin.py
fakeredis/commands_mixins/list_mixin.py
fakeredis/commands_mixins/pubsub_mixin.py
fakeredis/commands_mixins/scripting_mixin.py
fakeredis/commands_mixins/server_mixin.py
fakeredis/commands_mixins/set_mixin.py
fakeredis/commands_mixins/sortedset_mixin.py
fakeredis/commands_mixins/streams_mixin.py
fakeredis/commands_mixins/string_mixin.py
fakeredis/commands_mixins/transactions_mixin.py
fakeredis/geo/__init__.py
fakeredis/geo/geohash.py
fakeredis/geo/haversine.py
fakeredis/model/__init__.py
fakeredis/model/_acl.py
fakeredis/model/_command_info.py
fakeredis/model/_expiring_members_set.py
fakeredis/model/_hash.py
fakeredis/model/_stream.py
fakeredis/model/_timeseries_model.py
fakeredis/model/_topk.py
fakeredis/model/_zset.py
fakeredis/server_specific_commands/__init__.py
fakeredis/server_specific_commands/dragonfly_mixin.py
fakeredis/stack/__init__.py
fakeredis/stack/_bf_mixin.py
fakeredis/stack/_cf_mixin.py
fakeredis/stack/_cms_mixin.py
fakeredis/stack/_json_mixin.py
fakeredis/stack/_tdigest_mixin.py
fakeredis/stack/_timeseries_mixin.py
fakeredis/stack/_topk_mixin.py
fakeredis/LICENSE
fakeredis-2.30.2.dist-info/METADATA
fakeredis-2.30.2.dist-info/WHEEL
fakeredis-2.30.2.dist-info/licenses/LICENSE
fakeredis-2.30.2.dist-info/RECORD
