Metadata-Version: 2.4
Name: fakeredis
Version: 2.30.2
Summary: Python implementation of redis API, can be used for testing purposes.
Project-URL: Homepage, https://github.com/cunla/fakeredis-py
Project-URL: Repository, https://github.com/cunla/fakeredis-py
Project-URL: Documentation, https://fakeredis.moransoftware.ca/
Project-URL: Bug Tracker, https://github.com/cunla/fakeredis-py/issues
Project-URL: Funding, https://github.com/sponsors/cunla
Author-email: Daniel Moran <daniel@moransoftware.ca>, Bruce Merry <bmerry@ska.ac.za>, James Saryerwinnie <js@jamesls.com>
Maintainer-email: Daniel Moran <daniel@moransoftware.ca>
License-Expression: BSD-3-Clause
License-File: LICENSE
Keywords: RedisBloom,RedisJson,RedisTimeSeries,dragonfly,redis,redis-stack,testing,valkey
Classifier: Development Status :: 5 - Production/Stable
Classifier: Development Status :: 6 - Mature
Classifier: Intended Audience :: Developers
Classifier: License :: OSI Approved :: BSD License
Classifier: Operating System :: OS Independent
Classifier: Programming Language :: Python
Classifier: Programming Language :: Python :: 3.9
Classifier: Programming Language :: Python :: 3.10
Classifier: Programming Language :: Python :: 3.11
Classifier: Programming Language :: Python :: 3.12
Classifier: Programming Language :: Python :: 3.13
Classifier: Topic :: Software Development :: Libraries :: Python Modules
Requires-Python: >=3.7
Requires-Dist: redis>=4.3; python_version > '3.8'
Requires-Dist: redis>=4; python_version < '3.8'
Requires-Dist: sortedcontainers<3,>=2
Requires-Dist: typing-extensions~=4.7; python_version < '3.11'
Provides-Extra: bf
Requires-Dist: pyprobables>=0.6; extra == 'bf'
Provides-Extra: cf
Requires-Dist: pyprobables>=0.6; extra == 'cf'
Provides-Extra: json
Requires-Dist: jsonpath-ng~=1.6; extra == 'json'
Provides-Extra: lua
Requires-Dist: lupa<3.0,>=2.1; extra == 'lua'
Provides-Extra: probabilistic
Requires-Dist: pyprobables>=0.6; extra == 'probabilistic'
Provides-Extra: valkey
Requires-Dist: valkey>=6; (python_version >= '3.8') and extra == 'valkey'
